rkt_ai_lib/AI.py
rkt_ai_lib/__init__.py
rkt_ai_lib-2.1.0.dist-info/LICENSE
rkt_ai_lib-2.1.0.dist-info/METADATA
rkt_ai_lib-2.1.0.dist-info/WHEEL
rkt_ai_lib-2.1.0.dist-info/top_level.txt
rkt_ai_lib-2.1.0.dist-info/RECORD
